neuralpde/model/cnn.py
neuralpde/model/solver.py
neuralpde-0.0.1.dist-info/LICENCE
neuralpde-0.0.1.dist-info/METADATA
neuralpde-0.0.1.dist-info/WHEEL
neuralpde-0.0.1.dist-info/top_level.txt
neuralpde-0.0.1.dist-info/RECORD
