Metadata-Version: 2.1
Name: neuralpde
Version: 0.0.1
Summary: Neuralpde combines differentiable ode solvers with CNNs to learn PDEs using the method of lines
Author-email: Andrzej Dulny <andrzej.dulny@protonmail.com>
Keywords: neuralpde,torch
Classifier: License :: OSI Approved :: MIT License
Classifier: Programming Language :: Python
Classifier: Programming Language :: Python :: 3
Requires-Python: >=3.9
License-File: LICENCE
Requires-Dist: torch
